e6py/__init__.py
e6py/client.py
e6py/const.py
e6py/errors.py
e6py/http/client.py
e6py/http/endpoints/__init__.py
e6py/http/endpoints/flags.py
e6py/http/endpoints/notes.py
e6py/http/endpoints/pools.py
e6py/http/endpoints/posts.py
e6py/http/endpoints/tags.py
e6py/http/route.py
e6py/mixins.py
e6py/models/__init__.py
e6py/models/flag.py
e6py/models/note.py
e6py/models/pool.py
e6py/models/post.py
e6py/models/tag.py
e6py/utils/converters.py
e6py/utils/hash.py
e6py/utils/serializer.py
e6py-0.1.2.dist-info/LICENSE
e6py-0.1.2.dist-info/WHEEL
e6py-0.1.2.dist-info/METADATA
e6py-0.1.2.dist-info/RECORD
